pemjh/__init__.py
pemjh/numbers/__init__.py
pemjh/numbers/numbers.py
pemjh.numbers-0.0.1.dist-info/DESCRIPTION.rst
pemjh.numbers-0.0.1.dist-info/METADATA
pemjh.numbers-0.0.1.dist-info/RECORD
pemjh.numbers-0.0.1.dist-info/WHEEL
pemjh.numbers-0.0.1.dist-info/metadata.json
pemjh.numbers-0.0.1.dist-info/top_level.txt
