Metadata-Version: 2.0
Name: pemjh.numbers
Version: 0.0.1
Summary: Numeric helper functions for Project Euler Challenges.
Home-page: none.non
Author: Matthew Hussey
Author-email: matthew.hussey@googlemail.com
License: None, private use by myself only
Keywords: python
Platform: UNKNOWN
Classifier: Development Status :: 1 - Planning
